clipclean/__init__.py
clipclean/__main__.py
clipclean/cleaner.py
clipclean/gui.py
clipclean/themes.py
clipclean-1.0.0.dist-info/licenses/LICENSE
clipclean-1.0.0.dist-info/METADATA
clipclean-1.0.0.dist-info/WHEEL
clipclean-1.0.0.dist-info/entry_points.txt
clipclean-1.0.0.dist-info/top_level.txt
clipclean-1.0.0.dist-info/RECORD
