Metadata-Version: 2.4
Name: clipclean
Version: 1.0.0
Summary: A simple GUI tool for cleaning text copied from LLM outputs
Home-page: https://github.com/kevinobytes/clipclean
Author: Kevin O'Connor
License: MIT
Project-URL: Homepage, https://github.com/kevinobytes/clipclean
Project-URL: Repository, https://github.com/kevinobytes/clipclean
Project-URL: Issues, https://github.com/kevinobytes/clipclean/issues
Keywords: text,cleaning,llm,ai,clipboard,gui
Classifier: Development Status :: 4 - Beta
Classifier: Intended Audience :: End Users/Desktop
Classifier: License :: OSI Approved :: MIT License
Classifier: Operating System :: OS Independent
Classifier: Programming Language :: Python :: 3
Classifier: Programming Language :: Python :: 3.8
Classifier: Programming Language :: Python :: 3.9
Classifier: Programming Language :: Python :: 3.10
Classifier: Programming Language :: Python :: 3.11
Classifier: Programming Language :: Python :: 3.12
Classifier: Topic :: Text Processing :: General
Classifier: Topic :: Utilities
Requires-Python: >=3.8
License-File: LICENSE
Requires-Dist: pyperclip>=1.8.0
Provides-Extra: dev
Requires-Dist: build; extra == "dev"
Requires-Dist: twine; extra == "dev"
Requires-Dist: pyinstaller; extra == "dev"
Dynamic: home-page
Dynamic: license-file
Dynamic: requires-python
